issutilities/__init__.py
issutilities/actions.py
issutilities/client.py
issutilities/colors.py
issutilities/craft.py
issutilities/directories.py
issutilities-0.1.13.dist-info/LICENSE
issutilities-0.1.13.dist-info/METADATA
issutilities-0.1.13.dist-info/WHEEL
issutilities-0.1.13.dist-info/top_level.txt
issutilities-0.1.13.dist-info/RECORD
