Metadata-Version: 2.1
Name: issutilities
Version: 0.1.13
Summary: A small utilities file made for issu's Discord bots.
Author: issu
Maintainer: issu
License: MIT License
Project-URL: GitHub, https://github.com/TheLivingPepsi/issutilities
Classifier: Programming Language :: Python :: 3.12
Requires-Python: >=3.12
License-File: LICENSE
Requires-Dist: discord >=2.3.2
Requires-Dist: wavelink >=3.2.0
Requires-Dist: roblox ==2.0.0
